{
  "name": "bem-components",
  "version": "2.5.1",
  "description": "BEM Components Library",
  "bugs": "https://github.com/bem/bem-components/issues",
  "main": "",
  "ignore": [
    ".bem/cache",
    ".enb/tmp",
    "node_modules",
    "libs"
  ],
  "dependencies": {
    "bem-core": "2.9.1"
  },
  "devDependencies": {
    "bem-pr": "~0.10.0"
  },
  "license": "MPL-2.0",
  "private": true,
  "homepage": "https://github.com/bem/bem-components",
  "_release": "2.5.1",
  "_resolution": {
    "type": "version",
    "tag": "v2.5.1",
    "commit": "14593ae7b092de847841d339b7b11439595414f3"
  },
  "_source": "https://github.com/bem/bem-components.git",
  "_target": "2.5.1",
  "_originalSource": "bem-components"
}